fyers_apiv3/__init__.py
fyers_apiv3/fyersModel.py
fyers_apiv3/fyers_logger.py
fyers_apiv3/FyersWebsocket/__init__.py
fyers_apiv3/FyersWebsocket/data_ws.py
fyers_apiv3/FyersWebsocket/defines.py
fyers_apiv3/FyersWebsocket/map.json
fyers_apiv3/FyersWebsocket/msg_pb2.py
fyers_apiv3/FyersWebsocket/order_ws.py
fyers_apiv3/FyersWebsocket/tbt_ws.py
fyers_apiv3-3.1.9.dist-info/licenses/LICENSE.txt
fyers_apiv3-3.1.9.dist-info/METADATA
fyers_apiv3-3.1.9.dist-info/WHEEL
fyers_apiv3-3.1.9.dist-info/top_level.txt
fyers_apiv3-3.1.9.dist-info/RECORD
